LICENSE
README.md
setup.py
easy_commit/__init__.py
easy_commit/cli.py
easy_commit/generator.py
easy_commit/providers.py
easy_commit.egg-info/PKG-INFO
easy_commit.egg-info/SOURCES.txt
easy_commit.egg-info/dependency_links.txt
easy_commit.egg-info/entry_points.txt
easy_commit.egg-info/requires.txt
easy_commit.egg-info/top_level.txt