Metadata-Version: 2.1
Name: easy-commit
Version: 0.2.1
Summary: AI-powered Git commit message generator
Home-page: https://github.com/PraNavKumAr01/easy_commit
Author: Pranav Kumar
Author-email: pranavkumarnair@gmail.com
Classifier: Programming Language :: Python :: 3
Classifier: License :: OSI Approved :: MIT License
Classifier: Operating System :: OS Independent
Requires-Python: >=3.7
License-File: LICENSE
